README.md
setup.py
pytrafficcontrol/__init__.py
pytrafficcontrol/bandCalc.py
pytrafficcontrol/test_case.py
pytrafficcontrol/traffic_control.py
pytrafficcontrol.egg-info/PKG-INFO
pytrafficcontrol.egg-info/SOURCES.txt
pytrafficcontrol.egg-info/dependency_links.txt
pytrafficcontrol.egg-info/requires.txt
pytrafficcontrol.egg-info/top_level.txt